{
  "display_name": "berserk",
  "type": "warrior",
  "desc": "this is a description.",
  "career_trait": "warp spasm",
  "special_trait": "",
  "drawback": "",
  "advances": {
    "skills":
      [
        "athletics", "folklore", "guile", "intimidate", "martial_melee",
        "resolve", "simple_melee", "simple_ranged", "toughness", "warfare"
      ],
    "bonus":
    [
      { "attribute": "brawn", "amount":  5 },
      { "attribute": "brawn", "amount":  5 },
      { "attribute": "combat", "amount":  5 },
      { "attribute": "combat", "amount":  5 },
      { "attribute": "intelligence", "amount":  5 },
      { "attribute": "willpower", "amount":  5 },
      { "attribute": "willpower", "amount":  5 }
    ],
    "talents":
    [
      "nerves_of_steel", "overwhelming_force", "run_amok"
    ]
  }
}